Metadata-Version: 2.1
Name: lordmatrixoid-module
Version: 1.0
Summary: An example Python package
Home-page: https://github.com/
Author: Lord Matrixoid
Author-email: mr.art.pro@mail.ru
License: BSD 2-clause
Platform: UNKNOWN
